taulukko/__init__.py
taulukko/__main__.py
taulukko/cli.py
taulukko/taulukko.py
taulukko-2023.10.21.dist-info/LICENSE
taulukko-2023.10.21.dist-info/METADATA
taulukko-2023.10.21.dist-info/WHEEL
taulukko-2023.10.21.dist-info/entry_points.txt
taulukko-2023.10.21.dist-info/top_level.txt
taulukko-2023.10.21.dist-info/RECORD
