Metadata-Version: 2.1
Name: taulukko
Version: 2023.10.21
Summary: Table (Finnish Taulukko) glued together to transform into hands-free living.
Author-email: Stefan Hagen <stefan@hagen.link>
Maintainer-email: Stefan Hagen <stefan@hagen.link>
Project-URL: Homepage, https://git.sr.ht/~sthagen/taulukko
Project-URL: Bug-Tracker, https://todo.sr.ht/~sthagen/taulukko
Project-URL: Documentation, https://codes.dilettant.life/docs/taulukko
Project-URL: Source-Code, https://git.sr.ht/~sthagen/taulukko
Project-URL: Test-Coverage, https://codes.dilettant.life/coverage/taulukko
Keywords: developer-tools,documentation-tools,html,markdown
Classifier: Development Status :: 3 - Alpha
Classifier: Intended Audience :: Developers
Classifier: License :: OSI Approved :: MIT License
Classifier: Programming Language :: Python :: 3.10
Classifier: Programming Language :: Python :: 3.11
Classifier: Programming Language :: Python :: 3.9
Requires-Python: >=3.9
License-File: LICENSE
Requires-Dist: pytablereader >=0.31.4
Requires-Dist: pytablewriter >=1.2.0
Requires-Dist: typer >=0.9.0
Provides-Extra: dev
Requires-Dist: black ; extra == 'dev'
Requires-Dist: coverage ; extra == 'dev'
Requires-Dist: hypothesis ; extra == 'dev'
Requires-Dist: mypy ; extra == 'dev'
Requires-Dist: pytest ; extra == 'dev'
Requires-Dist: pytest-cov ; extra == 'dev'
Requires-Dist: pytest-flake8 ; extra == 'dev'
Requires-Dist: ruff ; extra == 'dev'
